dddmisc/__init__.py
dddmisc/abstract.py
dddmisc/aggregate.py
dddmisc/decorators.py
dddmisc/exceptions/__init__.py
dddmisc/exceptions/core.py
dddmisc/exceptions/errors.py
dddmisc/messagebus/__init__.py
dddmisc/messagebus/abstract.py
dddmisc/messagebus/async_messagebus.py
dddmisc/messagebus/sync_messagebus.py
dddmisc/messages/__init__.py
dddmisc/messages/_fields.py
dddmisc/messages/core.py
dddmisc/messages/fields.py
dddmisc/messages/fields.pyi
dddmisc/messages/messages.py
dddmisc/messages/structure.py
dddmisc/repository/__init__.py
dddmisc/repository/decorators.py
dddmisc/repository/repository.py
dddmisc/tools.py
dddmisc/unit_of_work.py
ddd_misc-0.8.4.dist-info/WHEEL
ddd_misc-0.8.4.dist-info/METADATA
ddd_misc-0.8.4.dist-info/RECORD
