Metadata-Version: 2.1
Name: ddd-misc
Version: 0.8.4
Summary: Python EDA & DDD utilites
Author: Vladislav Vorobyov
Author-email: vladislav.vorobyov@gmail.com
Requires-Python: >=3.8,<4.0
Classifier: Programming Language :: Python :: 3
Classifier: Programming Language :: Python :: 3.8
Classifier: Programming Language :: Python :: 3.9
Classifier: Programming Language :: Python :: 3.10
Classifier: Programming Language :: Python :: 3.11
Requires-Dist: pytz
Requires-Dist: tenacity (>=8.0.1,<9.0.0)
Requires-Dist: yarl (>=1.7.2,<2.0.0)
